CHANGELOG.md
LICENSE
eguivalet_server/__init__.py
eguivalet_server/__main__.py
eguivalet_server/config.py
eguivalet_server/crud.py
eguivalet_server/database.py
eguivalet_server/main.py
eguivalet_server/models.py
eguivalet_server/openapi_extension.py
eguivalet_server/routes/__init__.py
eguivalet_server/routes/api/__init__.py
eguivalet_server/routes/api/v1/__init__.py
eguivalet_server/routes/api/v1/rooms.py
eguivalet_server/routes/api/v1/users.py
eguivalet_server/routes/other.py
eguivalet_server/routes/robots.txt
eguivalet_server/schemas.py
eguivalet_server/utility.py
logging.conf
eguivalet_server-0.2.1.dist-info/LICENSE
eguivalet_server-0.2.1.dist-info/WHEEL
eguivalet_server-0.2.1.dist-info/METADATA
eguivalet_server-0.2.1.dist-info/RECORD
