Metadata-Version: 2.1
Name: eguivalet-server
Version: 0.2.1
Summary: A server implementation for the EguiValet messaging service.
Home-page: https://pypi.org/project/5G00EV25-3001_server/
License: MIT
Keywords: api,communication,network,networking,python3,restful
Author: Lari Liuhamo
Author-email: lari.liuhamo+pypi@gmail.com
Maintainer: Juha Järvinen
Maintainer-email: juha.3.jarvinen@tuni.fi
Requires-Python: >=3.8,<4.0
Classifier: Development Status :: 3 - Alpha
Classifier: Environment :: Web Environment
Classifier: Framework :: FastAPI
Classifier: Intended Audience :: Developers
Classifier: Intended Audience :: Education
Classifier: Intended Audience :: Information Technology
Classifier: License :: OSI Approved :: MIT License
Classifier: Natural Language :: English
Classifier: Operating System :: OS Independent
Classifier: Programming Language :: Python :: 3
Classifier: Programming Language :: Python :: 3.8
Classifier: Programming Language :: Python :: 3.9
Classifier: Programming Language :: Python :: 3.10
Classifier: Programming Language :: Python :: 3.11
Classifier: Programming Language :: Python :: 3.10
Classifier: Programming Language :: Python :: 3.8
Classifier: Programming Language :: Python :: 3.9
Classifier: Programming Language :: Python :: Implementation :: CPython
Classifier: Programming Language :: SQL
Classifier: Topic :: Communications :: Chat
Classifier: Topic :: Security
Classifier: Typing :: Typed
Requires-Dist: SQLAlchemy (>=1.4.42,<2.0.0)
Requires-Dist: SQLAlchemy-Utils (>=0.38.2,<0.39.0)
Requires-Dist: fastapi[all] (>=0.85.1,<0.86.0)
Requires-Dist: python-multipart (>=0.0.5,<0.0.6)
Requires-Dist: requests (>=2.28.1,<3.0.0)
Requires-Dist: tomli (>=2.0.1,<3.0.0)
Requires-Dist: uvicorn (>=0.18.3,<0.19.0)
Project-URL: Changelog, https://github.com/Diapolo10/5G00EV25-3001_server/blob/main/CHANGELOG.md
Project-URL: Documentation, https://github.com/Diapolo10/5G00EV25-3001_server/tree/main/docs
Project-URL: Repository, https://github.com/Diapolo10/5G00EV25-3001_server
Project-URL: Source code, https://github.com/Diapolo10/5G00EV25-3001_server
Project-URL: Tracker, https://github.com/Diapolo10/5G00EV25-3001_server/issues
